jax_sklearn-0.1.5.dist-info/METADATA
jax_sklearn-0.1.5.dist-info/WHEEL
jax_sklearn-0.1.5.dist-info/licenses/COPYING
xlearn/_cyutility.cpython-313-darwin.so
xlearn/_built_with_meson.py
xlearn/_isotonic.cpython-313-darwin.so
xlearn/__check_build/_check_build.cpython-313-darwin.so
xlearn/_loss/_loss.cpython-313-darwin.so
xlearn/utils/sparsefuncs_fast.cpython-313-darwin.so
xlearn/utils/_cython_blas.cpython-313-darwin.so
xlearn/utils/arrayfuncs.cpython-313-darwin.so
xlearn/utils/murmurhash.cpython-313-darwin.so
xlearn/utils/_fast_dict.cpython-313-darwin.so
xlearn/utils/_openmp_helpers.cpython-313-darwin.so
xlearn/utils/_random.cpython-313-darwin.so
xlearn/utils/_typedefs.cpython-313-darwin.so
xlearn/utils/_heap.cpython-313-darwin.so
xlearn/utils/_sorting.cpython-313-darwin.so
xlearn/utils/_vector_sentinel.cpython-313-darwin.so
xlearn/utils/_isfinite.cpython-313-darwin.so
xlearn/utils/_seq_dataset.cpython-313-darwin.so
xlearn/utils/_weight_vector.cpython-313-darwin.so
xlearn/metrics/_dist_metrics.pxd
xlearn/metrics/_dist_metrics.cpython-313-darwin.so
xlearn/metrics/_pairwise_fast.cpython-313-darwin.so
xlearn/metrics/_pairwise_distances_reduction/_datasets_pair.cpython-313-darwin.so
xlearn/metrics/_pairwise_distances_reduction/_base.cpython-313-darwin.so
xlearn/metrics/_pairwise_distances_reduction/_middle_term_computer.cpython-313-darwin.so
xlearn/metrics/_pairwise_distances_reduction/_argkmin.cpython-313-darwin.so
xlearn/metrics/_pairwise_distances_reduction/_radius_neighbors.cpython-313-darwin.so
xlearn/metrics/_pairwise_distances_reduction/_argkmin_classmode.cpython-313-darwin.so
xlearn/metrics/_pairwise_distances_reduction/_radius_neighbors_classmode.cpython-313-darwin.so
xlearn/metrics/cluster/_expected_mutual_info_fast.cpython-313-darwin.so
xlearn/cluster/_dbscan_inner.cpython-313-darwin.so
xlearn/cluster/_hierarchical_fast.cpython-313-darwin.so
xlearn/cluster/_k_means_common.cpython-313-darwin.so
xlearn/cluster/_k_means_lloyd.cpython-313-darwin.so
xlearn/cluster/_k_means_elkan.cpython-313-darwin.so
xlearn/cluster/_k_means_minibatch.cpython-313-darwin.so
jax_sklearn-0.1.5.dist-info/RECORD
