Metadata-Version: 2.4
Name: jax-sklearn
Version: 0.1.5
Summary: JAX-accelerated machine learning library with scikit-learn compatibility
Maintainer-Email: XLearn developers <xlearn@python.org>
License-Expression: BSD-3-Clause
License-File: COPYING
Classifier: Intended Audience :: Science/Research
Classifier: Intended Audience :: Developers
Classifier: Programming Language :: C
Classifier: Programming Language :: Python
Classifier: Topic :: Software Development
Classifier: Topic :: Scientific/Engineering
Classifier: Development Status :: 5 - Production/Stable
Classifier: Operating System :: Microsoft :: Windows
Classifier: Operating System :: POSIX
Classifier: Operating System :: Unix
Classifier: Operating System :: MacOS
Classifier: Programming Language :: Python :: 3
Classifier: Programming Language :: Python :: 3.10
Classifier: Programming Language :: Python :: 3.11
Classifier: Programming Language :: Python :: 3.12
Classifier: Programming Language :: Python :: 3.13
Classifier: Programming Language :: Python :: Implementation :: CPython
Project-URL: homepage, https://jax-sklearn.org
Project-URL: source, https://github.com/chenxingqiang/jax-sklearn
Project-URL: download, https://pypi.org/project/jax-sklearn/#files
Project-URL: tracker, https://github.com/chenxingqiang/jax-sklearn/issues
Project-URL: release notes, https://jax-sklearn.org/stable/whats_new
Requires-Python: >=3.10
Requires-Dist: numpy>=1.24.0
Requires-Dist: scipy>=1.10.0
Requires-Dist: joblib>=1.2.0
Requires-Dist: threadpoolctl>=3.1.0
Requires-Dist: jax>=0.4.20
Requires-Dist: jaxlib>=0.4.20
Provides-Extra: build
Requires-Dist: numpy>=1.24.0; extra == "build"
Requires-Dist: scipy>=1.10.0; extra == "build"
Requires-Dist: cython>=3.0.10; extra == "build"
Requires-Dist: meson-python>=0.17.1; extra == "build"
Provides-Extra: install
Requires-Dist: numpy>=1.24.0; extra == "install"
Requires-Dist: scipy>=1.10.0; extra == "install"
Requires-Dist: joblib>=1.2.0; extra == "install"
Requires-Dist: threadpoolctl>=3.1.0; extra == "install"
Requires-Dist: jax>=0.4.20; extra == "install"
Requires-Dist: jaxlib>=0.4.20; extra == "install"
Provides-Extra: jax
Requires-Dist: jax>=0.4.20; extra == "jax"
Requires-Dist: jaxlib>=0.4.20; extra == "jax"
Provides-Extra: jax-cpu
Requires-Dist: jax[cpu]>=0.4.20; extra == "jax-cpu"
Provides-Extra: jax-gpu
Requires-Dist: jax[gpu]>=0.4.20; extra == "jax-gpu"
Provides-Extra: benchmark
Requires-Dist: matplotlib>=3.5.0; extra == "benchmark"
Requires-Dist: pandas>=1.4.0; extra == "benchmark"
Requires-Dist: memory_profiler>=0.57.0; extra == "benchmark"
Provides-Extra: docs
Requires-Dist: matplotlib>=3.5.0; extra == "docs"
Requires-Dist: scikit-image>=0.19.0; extra == "docs"
Requires-Dist: pandas>=1.4.0; extra == "docs"
Requires-Dist: seaborn>=0.9.0; extra == "docs"
Requires-Dist: memory_profiler>=0.57.0; extra == "docs"
Requires-Dist: sphinx>=7.3.7; extra == "docs"
Requires-Dist: sphinx-copybutton>=0.5.2; extra == "docs"
Requires-Dist: sphinx-gallery>=0.17.1; extra == "docs"
Requires-Dist: numpydoc>=1.2.0; extra == "docs"
Requires-Dist: Pillow>=8.4.0; extra == "docs"
Requires-Dist: pooch>=1.6.0; extra == "docs"
Requires-Dist: sphinx-prompt>=1.4.0; extra == "docs"
Requires-Dist: sphinxext-opengraph>=0.9.1; extra == "docs"
Requires-Dist: plotly>=5.14.0; extra == "docs"
Requires-Dist: polars>=0.20.30; extra == "docs"
Requires-Dist: sphinx-design>=0.5.0; extra == "docs"
Requires-Dist: sphinx-design>=0.6.0; extra == "docs"
Requires-Dist: sphinxcontrib-sass>=0.3.4; extra == "docs"
Requires-Dist: pydata-sphinx-theme>=0.15.3; extra == "docs"
Requires-Dist: sphinx-remove-toctrees>=1.0.0.post1; extra == "docs"
Requires-Dist: towncrier>=24.8.0; extra == "docs"
Provides-Extra: examples
Requires-Dist: matplotlib>=3.5.0; extra == "examples"
Requires-Dist: scikit-image>=0.19.0; extra == "examples"
Requires-Dist: pandas>=1.4.0; extra == "examples"
Requires-Dist: seaborn>=0.9.0; extra == "examples"
Requires-Dist: pooch>=1.6.0; extra == "examples"
Requires-Dist: plotly>=5.14.0; extra == "examples"
Provides-Extra: tests
Requires-Dist: matplotlib>=3.5.0; extra == "tests"
Requires-Dist: scikit-image>=0.19.0; extra == "tests"
Requires-Dist: pandas>=1.4.0; extra == "tests"
Requires-Dist: pytest>=7.1.2; extra == "tests"
Requires-Dist: pytest-cov>=2.9.0; extra == "tests"
Requires-Dist: ruff>=0.11.7; extra == "tests"
Requires-Dist: mypy>=1.15; extra == "tests"
Requires-Dist: pyamg>=4.2.1; extra == "tests"
Requires-Dist: polars>=0.20.30; extra == "tests"
Requires-Dist: pyarrow>=12.0.0; extra == "tests"
Requires-Dist: numpydoc>=1.2.0; extra == "tests"
Requires-Dist: pooch>=1.6.0; extra == "tests"
Provides-Extra: maintenance
Requires-Dist: conda-lock==3.0.1; extra == "maintenance"
